{
  "friend": [
    {
      "id": "12",
      "name": "松本 大輔",
      "email": "daisuke.matsumoto@example.com",
      "phone": "080-2222-3333",
      "address": "大阪府大阪市2-2-2",
      "birthday": "1990-12-12",
      "memo": "大学の先輩"
    },
    {
      "id": "13",
      "name": "山本 美優",
      "email": "miyu.yamamoto@example.com",
      "phone": "070-3333-4444",
      "address": "神奈川県横浜市3-3-3",
      "birthday": "1993-01-13",
      "memo": "趣味仲間"
    },
    {
      "id": "14",
      "name": "渡辺 健太",
      "email": "kenta.watanabe@example.com",
      "phone": "090-4444-5555",
      "address": "愛知県名古屋市4-4-4",
      "birthday": "1991-02-14",
      "memo": "会社の後輩"
    },
    {
      "id": "15",
      "name": "中川 さくら",
      "email": "sakura.nakagawa@example.com",
      "phone": "080-5555-6666",
      "address": "京都府京都市5-5-5",
      "birthday": "1994-03-15",
      "memo": "旅行仲間"
    },
    {
      "id": "18",
      "name": "藤田 剛",
      "email": "go.fujita@example.com",
      "phone": "080-8888-9999",
      "address": "北海道札幌市8-8-8",
      "birthday": "1997-06-18",
      "memo": "サークル仲間"
    },
    {
      "id": "19",
      "name": "小川 美咲",
      "email": "misaki.ogawa@example.com",
      "phone": "070-9999-0000",
      "address": "千葉県千葉市9-9-9",
      "birthday": "1998-07-19",
      "memo": "幼なじみ"
    },
    {
      "id": "20",
      "name": "村上 翔太",
      "email": "shota.murakami@example.com",
      "phone": "090-0000-1111",
      "address": "埼玉県さいたま市10-10-10",
      "birthday": "1999-08-20",
      "memo": "趣味のイベントで知り合った"
    },
    {
      "id": "21",
      "name": "高木 由美",
      "email": "yumi.takagi@example.com",
      "phone": "080-1111-2222",
      "address": "東京都新宿区11-11-11",
      "birthday": "2000-09-21",
      "memo": "高校の同級生"
    },
    {
      "id": "22",
      "name": "西村 拓也",
      "email": "takuya.nishimura@example.com",
      "phone": "070-2222-3333",
      "address": "大阪府堺市12-12-12",
      "birthday": "2001-10-22",
      "memo": "大学の友人"
    },
    {
      "id": "23",
      "name": "岡田 美穂",
      "email": "miho.okada@example.com",
      "phone": "090-3333-4444",
      "address": "神奈川県川崎市13-13-13",
      "birthday": "2002-11-23",
      "memo": "趣味仲間"
    },
    {
      "id": "24",
      "name": "加藤 大地",
      "email": "daichi.kato@example.com",
      "phone": "080-4444-5555",
      "address": "愛知県豊田市14-14-14",
      "birthday": "2003-12-24",
      "memo": "会社の同僚"
    },
    {
      "id": "25",
      "name": "斎藤 さやか",
      "email": "sayaka.saito@example.com",
      "phone": "070-5555-6666",
      "address": "京都府宇治市15-15-15",
      "birthday": "2004-01-25",
      "memo": "旅行仲間"
    },
    {
      "id": "27",
      "name": "長谷川 美紀",
      "email": "miki.hasegawa@example.com",
      "phone": "080-7777-8888",
      "address": "福岡県北九州市17-17-17",
      "birthday": "2006-03-27",
      "memo": "SNSで知り合った"
    },
    {
      "id": "28",
      "name": "木村 剛",
      "email": "go.kimura@example.com",
      "phone": "070-8888-9999",
      "address": "北海道旭川市18-18-18",
      "birthday": "2007-04-28",
      "memo": "サークル仲間"
    },
    {
      "id": "29",
      "name": "原田 美咲",
      "email": "misaki.harada@example.com",
      "phone": "090-9999-0000",
      "address": "千葉県船橋市19-19-19",
      "birthday": "2008-05-29",
      "memo": "幼なじみ"
    },
    {
      "id": "b5c0",
      "name": "山崎泰輔",
      "email": "t44150703@yahoo.co.jp",
      "phone": "08045358258",
      "address": "兵庫県神戸市灘区篠原本町3-1-19-103",
      "birthday": "2025-04-29",
      "memo": "test"
    },
    {
      "id": "7e64",
      "name": "山崎泰輔",
      "email": "t44150703@yahoo.co.jp",
      "phone": "08045358258",
      "address": "兵庫県神戸市灘区篠原本町3-1-19-103",
      "birthday": "2025-04-27",
      "memo": "test"
    },
    {
      "id": "774d",
      "name": "山崎泰輔",
      "email": "t44150703@yahoo.co.jp",
      "phone": "08045358258",
      "address": "兵庫県神戸市灘区篠原本町3-1-19-103",
      "birthday": "2025-04-29",
      "memo": "test"
    },
    {
      "id": "87c5",
      "name": "山崎泰輔",
      "email": "t44150703@yahoo.co.jp",
      "phone": "08045358258",
      "address": "兵庫県神戸市灘区篠原本町3-1-19-103",
      "birthday": "2025-04-29",
      "memo": "test"
    },
    {
      "id": "fccf",
      "name": "山崎泰輔",
      "email": "t44150703@yahoo.co.jp",
      "phone": "08045358258",
      "address": "兵庫県神戸市灘区篠原本町3-1-19-103",
      "birthday": "2025-04-28",
      "memo": "test"
    },
    {
      "id": "fb6a",
      "name": "山崎泰輔",
      "email": "t44150703@yahoo.co.jp",
      "phone": "08045358258",
      "address": "兵庫県神戸市灘区篠原本町3-1-19-103",
      "birthday": "2025-05-08",
      "memo": "test"
    },
    {
      "id": "15a3",
      "name": "山崎泰輔",
      "email": "t44150703@yahoo.co.jp",
      "phone": "08045358258",
      "address": "兵庫県神戸市灘区篠原本町3-1-19-103",
      "birthday": "2025-04-30",
      "memo": "test"
    },
    {
      "id": "98a0",
      "name": "山崎泰輔",
      "email": "t44150703@yahoo.co.jp",
      "phone": "08045358258",
      "address": "兵庫県神戸市灘区篠原本町3-1-19-103",
      "birthday": "2025-05-08",
      "memo": "test"
    },
    {
      "id": "91ee",
      "name": "山崎泰輔",
      "email": "t44150703@yahoo.co.jp",
      "phone": "08045358258",
      "address": "兵庫県神戸市灘区篠原本町3-1-19-103",
      "birthday": "2025-05-07",
      "memo": "test"
    },
    {
      "id": "cacd",
      "name": "山崎泰輔",
      "email": "t44150703@yahoo.co.jp",
      "phone": "08045358258",
      "address": "兵庫県神戸市灘区篠原本町3-1-19-103",
      "birthday": "",
      "memo": "test"
    },
    {
      "id": "1447",
      "name": "山崎泰輔",
      "email": "t44150703@yahoo.co.jp",
      "phone": "08045358258",
      "address": "兵庫県神戸市灘区篠原本町3-1-19-103",
      "birthday": "2025-04-30",
      "memo": "test"
    },
    {
      "id": "982c",
      "name": "山崎泰輔",
      "email": "t44150703@yahoo.co.jp",
      "phone": "08045358258",
      "address": "兵庫県神戸市灘区篠原本町3-1-19-103",
      "birthday": "2025-04-30",
      "memo": "test"
    },
    {
      "id": "3168",
      "name": "山崎泰輔",
      "email": "t44150703@yahoo.co.jp",
      "phone": "08045358258",
      "address": "兵庫県神戸市灘区篠原本町3-1-19-103",
      "birthday": "2025-04-30",
      "memo": ""
    },
    {
      "id": "4e09",
      "name": "山崎泰輔",
      "email": "t44150703@yahoo.co.jp",
      "phone": "08045358258",
      "address": "兵庫県神戸市灘区篠原本町3-1-19-103",
      "birthday": "2025-04-29",
      "memo": "test"
    },
    {
      "id": "a101",
      "name": "田中 一郎",
      "email": "ichiro.tanaka@example.com",
      "phone": "080-1234-5678",
      "address": "東京都港区1-1-1",
      "birthday": "1980-01-01",
      "memo": "高校の同級生"
    },
    {
      "id": "a102",
      "name": "鈴木 次郎",
      "email": "jiro.suzuki@example.com",
      "phone": "090-2345-6789",
      "address": "大阪府大阪市2-2-2",
      "birthday": "1981-02-02",
      "memo": "大学の友人"
    },
    {
      "id": "a103",
      "name": "佐藤 三郎",
      "email": "saburo.sato@example.com",
      "phone": "070-3456-7890",
      "address": "愛知県名古屋市3-3-3",
      "birthday": "1982-03-03",
      "memo": "会社の同僚"
    },
    {
      "id": "a104",
      "name": "高橋 四郎",
      "email": "shiro.takahashi@example.com",
      "phone": "080-4567-8901",
      "address": "北海道札幌市4-4-4",
      "birthday": "1983-04-04",
      "memo": "趣味仲間"
    },
    {
      "id": "a105",
      "name": "伊藤 五郎",
      "email": "goro.ito@example.com",
      "phone": "090-5678-9012",
      "address": "福岡県福岡市5-5-5",
      "birthday": "1984-05-05",
      "memo": "旅行仲間"
    },
    {
      "id": "a106",
      "name": "渡辺 六郎",
      "email": "rokuro.watanabe@example.com",
      "phone": "070-6789-0123",
      "address": "京都府京都市6-6-6",
      "birthday": "1985-06-06",
      "memo": "バイト先の友人"
    },
    {
      "id": "a107",
      "name": "山本 七美",
      "email": "nanami.yamamoto@example.com",
      "phone": "080-7890-1234",
      "address": "神奈川県横浜市7-7-7",
      "birthday": "1986-07-07",
      "memo": "SNSで知り合った"
    },
    {
      "id": "a108",
      "name": "中村 八重子",
      "email": "yaeko.nakamura@example.com",
      "phone": "090-8901-2345",
      "address": "兵庫県神戸市8-8-8",
      "birthday": "1987-08-08",
      "memo": "サークル仲間"
    },
    {
      "id": "a109",
      "name": "小林 九郎",
      "email": "kurou.kobayashi@example.com",
      "phone": "070-9012-3456",
      "address": "千葉県千葉市9-9-9",
      "birthday": "1988-09-09",
      "memo": "幼なじみ"
    },
    {
      "id": "a110",
      "name": "加藤 十子",
      "email": "tokoko.kato@example.com",
      "phone": "080-0123-4567",
      "address": "埼玉県さいたま市10-10-10",
      "birthday": "1989-10-10",
      "memo": "高校の先輩"
    },
    {
      "id": "a111",
      "name": "佐々木 一美",
      "email": "kazumi.sasaki@example.com",
      "phone": "080-1111-2223",
      "address": "東京都世田谷区11-11-12",
      "birthday": "1990-01-11",
      "memo": "高校の友人"
    },
    {
      "id": "a112",
      "name": "山田 太郎",
      "email": "taro.yamada@example.com",
      "phone": "090-2222-3334",
      "address": "大阪府吹田市12-12-13",
      "birthday": "1991-02-12",
      "memo": "大学の友人"
    },
    {
      "id": "a113",
      "name": "田村 美咲",
      "email": "misaki.tamura@example.com",
      "phone": "070-3333-4445",
      "address": "愛知県岡崎市13-13-14",
      "birthday": "1992-03-13",
      "memo": "会社の同僚"
    },
    {
      "id": "a114",
      "name": "井上 剛",
      "email": "go.inoue@example.com",
      "phone": "080-4444-5556",
      "address": "北海道函館市14-14-15",
      "birthday": "1993-04-14",
      "memo": "趣味仲間"
    },
    {
      "id": "a115",
      "name": "松田 さくら",
      "email": "sakura.matsuda@example.com",
      "phone": "090-5555-6667",
      "address": "福岡県久留米市15-15-16",
      "birthday": "1994-05-15",
      "memo": "旅行仲間"
    },
    {
      "id": "a116",
      "name": "大西 亮太",
      "email": "ryota.onishi@example.com",
      "phone": "070-6666-7778",
      "address": "京都府舞鶴市16-16-17",
      "birthday": "1995-06-16",
      "memo": "バイト先の友人"
    },
    {
      "id": "a118",
      "name": "村田 剛志",
      "email": "tsuyoshi.murata@example.com",
      "phone": "090-8888-9990",
      "address": "兵庫県姫路市18-18-19",
      "birthday": "1997-08-18",
      "memo": "サークル仲間"
    },
    {
      "id": "a119",
      "name": "石田 美咲",
      "email": "misaki.ishida@example.com",
      "phone": "070-9999-0001",
      "address": "千葉県松戸市19-19-20",
      "birthday": "1998-09-19",
      "memo": "幼なじみ"
    },
    {
      "id": "a120",
      "name": "藤井 翔太",
      "email": "shota.fujii@example.com",
      "phone": "080-0000-1112",
      "address": "埼玉県川口市20-20-21",
      "birthday": "1999-10-20",
      "memo": "高校の先輩"
    }
  ]
}